<?xml version="1.0" encoding="UTF-8"?>
<nite:root xmlns:nite="http://nite.sourceforge.net/" id="move.q6ec5.g">
<move cont="false_cont" interj="false_interj" rep="none" aban="false_aban" meta="false_meta" id="q6ec5.g.move.1"  label="ready"><nite:child href="q6ec5.g.timed-units.xml#id(q6ec5g.1)..id(q6ec5g.4)"/></move>
<ims id="q6ec5.g.move.1.5" ><nite:child href="q6ec5.g.timed-units.xml#id(q6ec5g.5)"/></ims>
<move cont="false_cont" interj="false_interj" rep="none" aban="false_aban" meta="false_meta" id="q6ec5.g.move.2"  label="query_yn"><nite:child href="q6ec5.g.timed-units.xml#id(q6ec5g.6)..id(q6ec5g.14)"/></move>
<ims id="q6ec5.g.move.3.5" ><nite:child href="q6ec5.g.timed-units.xml#id(q6ec5g.15)"/></ims>
<move cont="false_cont" interj="false_interj" rep="none" aban="false_aban" meta="false_meta" id="q6ec5.g.move.4"  label="reply_w"><nite:child href="q6ec5.g.timed-units.xml#id(q6ec5g.16)..id(q6ec5g.21)"/></move>
<ims id="q6ec5.g.move.5.5" ><nite:child href="q6ec5.g.timed-units.xml#id(q6ec5g.22)..id(q6ec5g.24)"/></ims>
<move cont="false_cont" interj="false_interj" rep="none" aban="false_aban" meta="false_meta" id="q6ec5.g.move.6"  label="ready"><nite:child href="q6ec5.g.timed-units.xml#id(q6ec5g.25)..id(q6ec5g.29)"/></move>
<ims id="q6ec5.g.move.6.5" ><nite:child href="q6ec5.g.timed-units.xml#id(q6ec5g.31)"/></ims>
<move cont="false_cont" interj="false_interj" rep="none" aban="false_aban" meta="false_meta" id="q6ec5.g.move.7"  label="query_yn"><nite:child href="q6ec5.g.timed-units.xml#id(q6ec5g.32)..id(q6ec5g.40)"/></move>
<ims id="q6ec5.g.move.9.5" ><nite:child href="q6ec5.g.timed-units.xml#id(q6ec5g.42)..id(q6ec5g.44)"/></ims>
<move cont="false_cont" interj="false_interj" rep="none" aban="false_aban" meta="false_meta" id="q6ec5.g.move.10"  label="ready"><nite:child href="q6ec5.g.timed-units.xml#id(q6ec5g.45)..id(q6ec5g.47)"/></move>
<ims id="q6ec5.g.move.10.5" ><nite:child href="q6ec5.g.timed-units.xml#id(q6ec5g.49)..id(q6ec5g.50)"/></ims>
<move cont="false_cont" interj="false_interj" rep="none" aban="false_aban" meta="false_meta" id="q6ec5.g.move.11"  label="instruct"><nite:child href="q6ec5.g.timed-units.xml#id(q6ec5g.51)..id(q6ec5g.72)"/></move>
<ims id="q6ec5.g.move.12.5" ><nite:child href="q6ec5.g.timed-units.xml#id(q6ec5g.74)"/></ims>
<move cont="false_cont" interj="false_interj" rep="none" aban="false_aban" meta="false_meta" id="q6ec5.g.move.13"  label="instruct"><nite:child href="q6ec5.g.timed-units.xml#id(q6ec5g.75)..id(q6ec5g.79)"/></move>
<ims id="q6ec5.g.move.14.5" ><nite:child href="q6ec5.g.timed-units.xml#id(q6ec5g.80)"/></ims>
<move interj="false_interj" rep="none" aban="false_aban" meta="false_meta" id="q6ec5.g.move.15"  label="instruct" cont="true_cont"><nite:child href="q6ec5.g.timed-units.xml#id(q6ec5g.81)..id(q6ec5g.92)"/></move>
<ims id="q6ec5.g.move.18.5" ><nite:child href="q6ec5.g.timed-units.xml#id(q6ec5g.93)"/></ims>
<move cont="false_cont" interj="false_interj" rep="none" aban="false_aban" meta="false_meta" id="q6ec5.g.move.19"  label="reply_y"><nite:child href="q6ec5.g.timed-units.xml#id(q6ec5g.94)"/></move>
<ims id="q6ec5.g.move.19.4" ><nite:child href="q6ec5.g.timed-units.xml#id(q6ec5g.95)"/></ims>
<move cont="false_cont" interj="false_interj" rep="none" aban="false_aban" meta="false_meta" id="q6ec5.g.move.19.9"  label="instruct"><nite:child href="q6ec5.g.timed-units.xml#id(q6ec5g.96)..id(q6ec5g.100)"/></move>
<ims id="q6ec5.g.move.20.5" ><nite:child href="q6ec5.g.timed-units.xml#id(q6ec5g.101)"/></ims>
<move interj="false_interj" rep="none" aban="false_aban" meta="false_meta" id="q6ec5.g.move.21"  label="instruct" cont="true_cont"><nite:child href="q6ec5.g.timed-units.xml#id(q6ec5g.102)..id(q6ec5g.119)"/></move>
<ims id="q6ec5.g.move.22.5" ><nite:child href="q6ec5.g.timed-units.xml#id(q6ec5g.121)"/></ims>
<move cont="false_cont" interj="false_interj" rep="none" meta="false_meta" id="q6ec5.g.move.23"  label="instruct" aban="true_aban"><nite:child href="q6ec5.g.timed-units.xml#id(q6ec5g.122)..id(q6ec5g.132)"/></move>
<ims id="q6ec5.g.move.23.5" ><nite:child href="q6ec5.g.timed-units.xml#id(q6ec5g.133)"/></ims>
<move cont="false_cont" interj="false_interj" rep="none" aban="false_aban" meta="false_meta" id="q6ec5.g.move.24"  label="query_yn"><nite:child href="q6ec5.g.timed-units.xml#id(q6ec5g.134)..id(q6ec5g.139)"/></move>
<ims id="q6ec5.g.move.25.5" ><nite:child href="q6ec5.g.timed-units.xml#id(q6ec5g.141)..id(q6ec5g.145)"/></ims>
<move cont="false_cont" interj="false_interj" rep="none" aban="false_aban" meta="false_meta" id="q6ec5.g.move.26"  label="ready"><nite:child href="q6ec5.g.timed-units.xml#id(q6ec5g.146)"/></move>
<move interj="false_interj" rep="none" aban="false_aban" meta="false_meta" id="q6ec5.g.move.27"  label="instruct" cont="true_cont"><nite:child href="q6ec5.g.timed-units.xml#id(q6ec5g.148)..id(q6ec5g.159)"/></move>
<ims id="q6ec5.g.move.28.5" ><nite:child href="q6ec5.g.timed-units.xml#id(q6ec5g.161)..id(q6ec5g.163)"/></ims>
<move cont="false_cont" interj="false_interj" rep="none" aban="false_aban" meta="false_meta" id="q6ec5.g.move.29"  label="instruct"><nite:child href="q6ec5.g.timed-units.xml#id(q6ec5g.164)..id(q6ec5g.182)"/></move>
<ims id="q6ec5.g.move.30.5" ><nite:child href="q6ec5.g.timed-units.xml#id(q6ec5g.184)"/></ims>
<move cont="false_cont" interj="false_interj" rep="none" aban="false_aban" meta="false_meta" id="q6ec5.g.move.31"  label="query_yn"><nite:child href="q6ec5.g.timed-units.xml#id(q6ec5g.185)..id(q6ec5g.189)"/></move>
<ims id="q6ec5.g.move.32.5" ><nite:child href="q6ec5.g.timed-units.xml#id(q6ec5g.191)"/></ims>
<move interj="false_interj" rep="none" aban="false_aban" meta="false_meta" id="q6ec5.g.move.33"  label="query_yn" cont="true_cont"><nite:child href="q6ec5.g.timed-units.xml#id(q6ec5g.192)..id(q6ec5g.202)"/></move>
<ims id="q6ec5.g.move.34.5" ><nite:child href="q6ec5.g.timed-units.xml#id(q6ec5g.203)..id(q6ec5g.205)"/></ims>
<move cont="false_cont" interj="false_interj" rep="none" aban="false_aban" meta="false_meta" id="q6ec5.g.move.35"  label="ready"><nite:child href="q6ec5.g.timed-units.xml#id(q6ec5g.206)"/></move>
<move cont="false_cont" interj="false_interj" rep="none" aban="false_aban" meta="false_meta" id="q6ec5.g.move.36"  label="instruct"><nite:child href="q6ec5.g.timed-units.xml#id(q6ec5g.208)..id(q6ec5g.222)"/></move>
<ims id="q6ec5.g.move.38.5" ><nite:child href="q6ec5.g.timed-units.xml#id(q6ec5g.224)"/></ims>
<move cont="false_cont" interj="false_interj" rep="none" aban="false_aban" meta="false_meta" id="q6ec5.g.move.39"  label="reply_w"><nite:child href="q6ec5.g.timed-units.xml#id(q6ec5g.225)..id(q6ec5g.231)"/></move>
<ims id="q6ec5.g.move.40.5" ><nite:child href="q6ec5.g.timed-units.xml#id(q6ec5g.232)..id(q6ec5g.234)"/></ims>
<move interj="false_interj" rep="none" aban="false_aban" meta="false_meta" id="q6ec5.g.move.41"  label="instruct" cont="true_cont"><nite:child href="q6ec5.g.timed-units.xml#id(q6ec5g.235)..id(q6ec5g.256)"/></move>
<ims id="q6ec5.g.move.42.5" ><nite:child href="q6ec5.g.timed-units.xml#id(q6ec5g.257)"/></ims>
<move interj="false_interj" rep="none" aban="false_aban" meta="false_meta" id="q6ec5.g.move.43"  label="instruct" cont="true_cont"><nite:child href="q6ec5.g.timed-units.xml#id(q6ec5g.258)..id(q6ec5g.260)"/></move>
<ims id="q6ec5.g.move.43.5" ><nite:child href="q6ec5.g.timed-units.xml#id(q6ec5g.262)"/></ims>
<move cont="false_cont" interj="false_interj" rep="none" aban="false_aban" meta="false_meta" id="q6ec5.g.move.44"  label="align"><nite:child href="q6ec5.g.timed-units.xml#id(q6ec5g.263)..id(q6ec5g.265)"/></move>
<ims id="q6ec5.g.move.45.5" ><nite:child href="q6ec5.g.timed-units.xml#id(q6ec5g.266)..id(q6ec5g.268)"/></ims>
<move cont="false_cont" interj="false_interj" rep="none" aban="false_aban" meta="false_meta" id="q6ec5.g.move.46"  label="ready"><nite:child href="q6ec5.g.timed-units.xml#id(q6ec5g.269)"/></move>
<move cont="false_cont" interj="false_interj" rep="none" aban="false_aban" meta="false_meta" id="q6ec5.g.move.47"  label="query_yn"><nite:child href="q6ec5.g.timed-units.xml#id(q6ec5g.271)..id(q6ec5g.277)"/></move>
<ims id="q6ec5.g.move.49.5" ><nite:child href="q6ec5.g.timed-units.xml#id(q6ec5g.278)..id(q6ec5g.280)"/></ims>
<move cont="false_cont" interj="false_interj" rep="none" aban="false_aban" meta="false_meta" id="q6ec5.g.move.50"  label="reply_n"><nite:child href="q6ec5.g.timed-units.xml#id(q6ec5g.281)"/></move>
<ims id="q6ec5.g.move.52.5" ><nite:child href="q6ec5.g.timed-units.xml#id(q6ec5g.283)"/></ims>
<move cont="false_cont" interj="false_interj" rep="none" aban="false_aban" meta="false_meta" id="q6ec5.g.move.53"  label="query_yn"><nite:child href="q6ec5.g.timed-units.xml#id(q6ec5g.284)..id(q6ec5g.288)"/></move>
<ims id="q6ec5.g.move.54.5" ><nite:child href="q6ec5.g.timed-units.xml#id(q6ec5g.290)"/></ims>
<move cont="false_cont" interj="false_interj" rep="none" aban="false_aban" meta="false_meta" id="q6ec5.g.move.55"  label="reply_y"><nite:child href="q6ec5.g.timed-units.xml#id(q6ec5g.291)"/></move>
<ims id="q6ec5.g.move.57.5" ><nite:child href="q6ec5.g.timed-units.xml#id(q6ec5g.293)..id(q6ec5g.295)"/></ims>
<move cont="false_cont" interj="false_interj" rep="none" aban="false_aban" meta="false_meta" id="q6ec5.g.move.58"  label="ready"><nite:child href="q6ec5.g.timed-units.xml#id(q6ec5g.296)"/></move>
<move cont="false_cont" interj="false_interj" rep="none" meta="false_meta" id="q6ec5.g.move.59"  label="explain" aban="true_aban"><nite:child href="q6ec5.g.timed-units.xml#id(q6ec5g.297)..id(q6ec5g.298)"/></move>
<ims id="q6ec5.g.move.60.5" ><nite:child href="q6ec5.g.timed-units.xml#id(q6ec5g.299)"/></ims>
<move cont="false_cont" interj="false_interj" rep="none" aban="false_aban" meta="false_meta" id="q6ec5.g.move.61"  label="check"><nite:child href="q6ec5.g.timed-units.xml#id(q6ec5g.300)..id(q6ec5g.303)"/></move>
<ims id="q6ec5.g.move.62.5" ><nite:child href="q6ec5.g.timed-units.xml#id(q6ec5g.305)..id(q6ec5g.307)"/></ims>
<move cont="false_cont" interj="false_interj" rep="none" aban="false_aban" meta="false_meta" id="q6ec5.g.move.63"  label="ready"><nite:child href="q6ec5.g.timed-units.xml#id(q6ec5g.308)"/></move>
<ims id="q6ec5.g.move.63.5" ><nite:child href="q6ec5.g.timed-units.xml#id(q6ec5g.310)"/></ims>
<move cont="false_cont" interj="false_interj" rep="none" aban="false_aban" meta="false_meta" id="q6ec5.g.move.64"  label="explain"><nite:child href="q6ec5.g.timed-units.xml#id(q6ec5g.311)..id(q6ec5g.325)"/></move>
<ims id="q6ec5.g.move.64.5" ><nite:child href="q6ec5.g.timed-units.xml#id(q6ec5g.327)..id(q6ec5g.328)"/></ims>
<move cont="false_cont" interj="false_interj" rep="none" aban="false_aban" meta="false_meta" id="q6ec5.g.move.65"  label="align"><nite:child href="q6ec5.g.timed-units.xml#id(q6ec5g.329)..id(q6ec5g.331)"/></move>
<ims id="q6ec5.g.move.67.5" ><nite:child href="q6ec5.g.timed-units.xml#id(q6ec5g.332)"/></ims>
<move cont="false_cont" interj="false_interj" rep="none" aban="false_aban" meta="false_meta" id="q6ec5.g.move.68"  label="reply_y"><nite:child href="q6ec5.g.timed-units.xml#id(q6ec5g.333)..id(q6ec5g.341)"/></move>
<ims id="q6ec5.g.move.69.4" ><nite:child href="q6ec5.g.timed-units.xml#id(q6ec5g.342)..id(q6ec5g.343)"/></ims>
<move interj="false_interj" rep="none" aban="false_aban" meta="false_meta" id="q6ec5.g.move.69.5"  label="ready" cont="true_cont"><nite:child href="q6ec5.g.timed-units.xml#id(q6ec5g.344)"/></move>
<ims id="q6ec5.g.move.69.6" ><nite:child href="q6ec5.g.timed-units.xml#id(q6ec5g.345)..id(q6ec5g.347)"/></ims>
<move interj="false_interj" rep="none" aban="false_aban" meta="false_meta" id="q6ec5.g.move.69.7"  label="uncodable" cont="true_cont"><nite:child href="q6ec5.g.timed-units.xml#id(q6ec5g.348)"/></move>
<ims id="q6ec5.g.move.70.1" ><nite:child href="q6ec5.g.timed-units.xml#id(q6ec5g.350)..id(q6ec5g.351)"/></ims>
<move interj="false_interj" rep="none" aban="false_aban" meta="false_meta" id="q6ec5.g.move.70.2"  label="ready" cont="true_cont"><nite:child href="q6ec5.g.timed-units.xml#id(q6ec5g.352)..id(q6ec5g.353)"/></move>
<ims id="q6ec5.g.move.70.4" ><nite:child href="q6ec5.g.timed-units.xml#id(q6ec5g.354)..id(q6ec5g.356)"/></ims>
<move interj="false_interj" rep="none" aban="false_aban" meta="false_meta" id="q6ec5.g.move.70.9"  label="explain" cont="true_cont"><nite:child href="q6ec5.g.timed-units.xml#id(q6ec5g.357)..id(q6ec5g.369)"/></move>
<ims id="q6ec5.g.move.71.5" ><nite:child href="q6ec5.g.timed-units.xml#id(q6ec5g.371)..id(q6ec5g.373)"/></ims>
<move cont="false_cont" interj="false_interj" rep="none" aban="false_aban" meta="false_meta" id="q6ec5.g.move.72"  label="instruct"><nite:child href="q6ec5.g.timed-units.xml#id(q6ec5g.374)..id(q6ec5g.383)"/></move>
<ims id="q6ec5.g.move.73.5" ><nite:child href="q6ec5.g.timed-units.xml#id(q6ec5g.384)"/></ims>
<move interj="false_interj" rep="none" aban="false_aban" meta="false_meta" id="q6ec5.g.move.74"  label="instruct" cont="true_cont"><nite:child href="q6ec5.g.timed-units.xml#id(q6ec5g.385)..id(q6ec5g.387)"/></move>
<ims id="q6ec5.g.move.75.5" ><nite:child href="q6ec5.g.timed-units.xml#id(q6ec5g.388)"/></ims>
<move cont="false_cont" interj="false_interj" rep="none" aban="false_aban" meta="false_meta" id="q6ec5.g.move.76"  label="reply_y"><nite:child href="q6ec5.g.timed-units.xml#id(q6ec5g.389)..id(q6ec5g.391)"/></move>
<ims id="q6ec5.g.move.77.5" ><nite:child href="q6ec5.g.timed-units.xml#id(q6ec5g.392)"/></ims>
<move cont="false_cont" interj="false_interj" rep="none" aban="false_aban" meta="false_meta" id="q6ec5.g.move.78"  label="instruct"><nite:child href="q6ec5.g.timed-units.xml#id(q6ec5g.393)..id(q6ec5g.395)"/></move>
<ims id="q6ec5.g.move.79.5" ><nite:child href="q6ec5.g.timed-units.xml#id(q6ec5g.396)"/></ims>
<move interj="false_interj" rep="none" aban="false_aban" meta="false_meta" id="q6ec5.g.move.80"  label="instruct" cont="true_cont"><nite:child href="q6ec5.g.timed-units.xml#id(q6ec5g.397)..id(q6ec5g.401)"/></move>
<ims id="q6ec5.g.move.80.5" ><nite:child href="q6ec5.g.timed-units.xml#id(q6ec5g.403)..id(q6ec5g.405)"/></ims>
<move cont="false_cont" interj="false_interj" rep="none" aban="false_aban" meta="false_meta" id="q6ec5.g.move.81"  label="instruct"><nite:child href="q6ec5.g.timed-units.xml#id(q6ec5g.406)..id(q6ec5g.411)"/></move>
<ims id="q6ec5.g.move.83.5" ><nite:child href="q6ec5.g.timed-units.xml#id(q6ec5g.412)"/></ims>
<move cont="false_cont" interj="false_interj" rep="none" aban="false_aban" meta="false_meta" id="q6ec5.g.move.84"  label="reply_y"><nite:child href="q6ec5.g.timed-units.xml#id(q6ec5g.413)"/></move>
<move interj="false_interj" rep="none" aban="false_aban" meta="false_meta" id="q6ec5.g.move.85"  label="instruct" cont="true_cont"><nite:child href="q6ec5.g.timed-units.xml#id(q6ec5g.415)..id(q6ec5g.432)"/></move>
<ims id="q6ec5.g.move.86.5" ><nite:child href="q6ec5.g.timed-units.xml#id(q6ec5g.434)..id(q6ec5g.436)"/></ims>
<move cont="false_cont" interj="false_interj" rep="none" aban="false_aban" meta="false_meta" id="q6ec5.g.move.87"  label="instruct"><nite:child href="q6ec5.g.timed-units.xml#id(q6ec5g.437)..id(q6ec5g.449)"/></move>
<ims id="q6ec5.g.move.88.5" ><nite:child href="q6ec5.g.timed-units.xml#id(q6ec5g.450)"/></ims>
<move interj="false_interj" rep="none" aban="false_aban" meta="false_meta" id="q6ec5.g.move.89"  label="instruct" cont="true_cont"><nite:child href="q6ec5.g.timed-units.xml#id(q6ec5g.451)..id(q6ec5g.461)"/></move>
<ims id="q6ec5.g.move.90.5" ><nite:child href="q6ec5.g.timed-units.xml#id(q6ec5g.462)"/></ims>
<move interj="false_interj" rep="none" aban="false_aban" meta="false_meta" id="q6ec5.g.move.91"  label="instruct" cont="true_cont"><nite:child href="q6ec5.g.timed-units.xml#id(q6ec5g.463)..id(q6ec5g.471)"/></move>
<ims id="q6ec5.g.move.94.5" ><nite:child href="q6ec5.g.timed-units.xml#id(q6ec5g.472)..id(q6ec5g.474)"/></ims>
<move cont="false_cont" interj="false_interj" rep="none" aban="false_aban" meta="false_meta" id="q6ec5.g.move.95"  label="reply_n"><nite:child href="q6ec5.g.timed-units.xml#id(q6ec5g.475)..id(q6ec5g.477)"/></move>
<ims id="q6ec5.g.move.96.5" ><nite:child href="q6ec5.g.timed-units.xml#id(q6ec5g.478)..id(q6ec5g.481)"/></ims>
<move interj="false_interj" rep="none" aban="false_aban" meta="false_meta" id="q6ec5.g.move.97"  label="instruct" cont="true_cont"><nite:child href="q6ec5.g.timed-units.xml#id(q6ec5g.482)..id(q6ec5g.492)"/></move>
<ims id="q6ec5.g.move.99.5" ><nite:child href="q6ec5.g.timed-units.xml#id(q6ec5g.493)..id(q6ec5g.495)"/></ims>
<move cont="false_cont" rep="none" aban="false_aban" meta="false_meta" id="q6ec5.g.move.100"  label="ready" interj="true_interj"><nite:child href="q6ec5.g.timed-units.xml#id(q6ec5g.496)..id(q6ec5g.497)"/></move>
<ims id="q6ec5.g.move.100.5" ><nite:child href="q6ec5.g.timed-units.xml#id(q6ec5g.499)..id(q6ec5g.500)"/></ims>
<move cont="false_cont" interj="false_interj" rep="none" aban="false_aban" meta="false_meta" id="q6ec5.g.move.101"  label="instruct"><nite:child href="q6ec5.g.timed-units.xml#id(q6ec5g.501)..id(q6ec5g.530)"/></move>
<ims id="q6ec5.g.move.102.5" ><nite:child href="q6ec5.g.timed-units.xml#id(q6ec5g.531)"/></ims>
<move rep="none" aban="false_aban" meta="false_meta" id="q6ec5.g.move.103"  label="instruct" interj="true_interj" cont="true_cont"><nite:child href="q6ec5.g.timed-units.xml#id(q6ec5g.532)"/></move>
<ims id="q6ec5.g.move.103.5" ><nite:child href="q6ec5.g.timed-units.xml#id(q6ec5g.533)..id(q6ec5g.534)"/></ims>
<move cont="false_cont" interj="false_interj" rep="none" aban="false_aban" meta="false_meta" id="q6ec5.g.move.104"  label="query_yn"><nite:child href="q6ec5.g.timed-units.xml#id(q6ec5g.535)..id(q6ec5g.540)"/></move>
<ims id="q6ec5.g.move.105.5" ><nite:child href="q6ec5.g.timed-units.xml#id(q6ec5g.542)..id(q6ec5g.543)"/></ims>
<move cont="false_cont" interj="false_interj" rep="none" aban="false_aban" id="q6ec5.g.move.106"  label="explain" meta="true_meta"><nite:child href="q6ec5.g.timed-units.xml#id(q6ec5g.544)..id(q6ec5g.552)"/></move>
<ims id="q6ec5.g.move.107.5" ><nite:child href="q6ec5.g.timed-units.xml#id(q6ec5g.553)..id(q6ec5g.554)"/></ims>
<move cont="false_cont" interj="false_interj" rep="none" aban="false_aban" meta="false_meta" id="q6ec5.g.move.108"  label="instruct"><nite:child href="q6ec5.g.timed-units.xml#id(q6ec5g.555)..id(q6ec5g.595)"/></move>
<ims id="q6ec5.g.move.111.5" ><nite:child href="q6ec5.g.timed-units.xml#id(q6ec5g.596)..id(q6ec5g.598)"/></ims>
<move interj="false_interj" rep="none" aban="false_aban" meta="false_meta" id="q6ec5.g.move.112"  label="instruct" cont="true_cont"><nite:child href="q6ec5.g.timed-units.xml#id(q6ec5g.599)..id(q6ec5g.602)"/></move>
<ims id="q6ec5.g.move.112.5" ><nite:child href="q6ec5.g.timed-units.xml#id(q6ec5g.604)..id(q6ec5g.607)"/></ims>
<move cont="false_cont" interj="false_interj" rep="none" aban="false_aban" meta="false_meta" id="q6ec5.g.move.113"  label="explain"><nite:child href="q6ec5.g.timed-units.xml#id(q6ec5g.608)..id(q6ec5g.619)"/></move>
<ims id="q6ec5.g.move.114.5" ><nite:child href="q6ec5.g.timed-units.xml#id(q6ec5g.620)"/></ims>
<move cont="false_cont" interj="false_interj" rep="none" aban="false_aban" meta="false_meta" id="q6ec5.g.move.115"  label="reply_w"><nite:child href="q6ec5.g.timed-units.xml#id(q6ec5g.621)..id(q6ec5g.625)"/></move>
<ims id="q6ec5.g.move.117.5" ><nite:child href="q6ec5.g.timed-units.xml#id(q6ec5g.626)..id(q6ec5g.628)"/></ims>
<move interj="false_interj" rep="none" aban="false_aban" meta="false_meta" id="q6ec5.g.move.118"  label="explain" cont="true_cont"><nite:child href="q6ec5.g.timed-units.xml#id(q6ec5g.629)..id(q6ec5g.641)"/></move>
<ims id="q6ec5.g.move.119.5" ><nite:child href="q6ec5.g.timed-units.xml#id(q6ec5g.642)..id(q6ec5g.644)"/></ims>
<move cont="false_cont" interj="false_interj" rep="none" aban="false_aban" meta="false_meta" id="q6ec5.g.move.120"  label="instruct"><nite:child href="q6ec5.g.timed-units.xml#id(q6ec5g.645)..id(q6ec5g.663)"/></move>
<ims id="q6ec5.g.move.121.5" ><nite:child href="q6ec5.g.timed-units.xml#id(q6ec5g.664)"/></ims>
<move cont="false_cont" interj="false_interj" rep="none" aban="false_aban" meta="false_meta" id="q6ec5.g.move.122"  label="reply_w"><nite:child href="q6ec5.g.timed-units.xml#id(q6ec5g.665)..id(q6ec5g.670)"/></move>
<ims id="q6ec5.g.move.123.5" ><nite:child href="q6ec5.g.timed-units.xml#id(q6ec5g.671)"/></ims>
<move cont="false_cont" interj="false_interj" rep="none" aban="false_aban" meta="false_meta" id="q6ec5.g.move.124"  label="instruct"><nite:child href="q6ec5.g.timed-units.xml#id(q6ec5g.672)..id(q6ec5g.680)"/></move>
<ims id="q6ec5.g.move.125.5" ><nite:child href="q6ec5.g.timed-units.xml#id(q6ec5g.681)"/></ims>
<move cont="false_cont" interj="false_interj" rep="none" aban="false_aban" meta="false_meta" id="q6ec5.g.move.126"  label="check"><nite:child href="q6ec5.g.timed-units.xml#id(q6ec5g.682)..id(q6ec5g.688)"/></move>
<ims id="q6ec5.g.move.127.5" ><nite:child href="q6ec5.g.timed-units.xml#id(q6ec5g.689)..id(q6ec5g.691)"/></ims>
<move interj="false_interj" rep="none" aban="false_aban" meta="false_meta" id="q6ec5.g.move.128"  label="instruct" cont="true_cont"><nite:child href="q6ec5.g.timed-units.xml#id(q6ec5g.692)..id(q6ec5g.700)"/></move>
<ims id="q6ec5.g.move.128.5" ><nite:child href="q6ec5.g.timed-units.xml#id(q6ec5g.702)"/></ims>
<move cont="false_cont" interj="false_interj" rep="none" aban="false_aban" meta="false_meta" id="q6ec5.g.move.129"  label="instruct"><nite:child href="q6ec5.g.timed-units.xml#id(q6ec5g.703)..id(q6ec5g.715)"/></move>
<ims id="q6ec5.g.move.129.5" ><nite:child href="q6ec5.g.timed-units.xml#id(q6ec5g.716)"/></ims>
<move cont="false_cont" interj="false_interj" rep="none" aban="false_aban" meta="false_meta" id="q6ec5.g.move.130"  label="explain"><nite:child href="q6ec5.g.timed-units.xml#id(q6ec5g.717)..id(q6ec5g.732)"/></move>
<ims id="q6ec5.g.move.131.5" ><nite:child href="q6ec5.g.timed-units.xml#id(q6ec5g.733)..id(q6ec5g.739)"/></ims>
<move cont="false_cont" interj="false_interj" rep="none" aban="false_aban" meta="false_meta" id="q6ec5.g.move.132"  label="ready"><nite:child href="q6ec5.g.timed-units.xml#id(q6ec5g.740)"/></move>
<move interj="false_interj" rep="none" aban="false_aban" meta="false_meta" id="q6ec5.g.move.133"  label="explain" cont="true_cont"><nite:child href="q6ec5.g.timed-units.xml#id(q6ec5g.742)..id(q6ec5g.760)"/></move>
<ims id="q6ec5.g.move.134.5" ><nite:child href="q6ec5.g.timed-units.xml#id(q6ec5g.761)..id(q6ec5g.763)"/></ims>
<move cont="false_cont" interj="false_interj" rep="none" aban="false_aban" meta="false_meta" id="q6ec5.g.move.135"  label="reply_y"><nite:child href="q6ec5.g.timed-units.xml#id(q6ec5g.764)..id(q6ec5g.766)"/></move>
<ims id="q6ec5.g.move.135.5" ><nite:child href="q6ec5.g.timed-units.xml#id(q6ec5g.767)..id(q6ec5g.768)"/></ims>
<move cont="false_cont" interj="false_interj" rep="none" aban="false_aban" meta="false_meta" id="q6ec5.g.move.136"  label="explain"><nite:child href="q6ec5.g.timed-units.xml#id(q6ec5g.769)..id(q6ec5g.776)"/></move>
<ims id="q6ec5.g.move.138.5" ><nite:child href="q6ec5.g.timed-units.xml#id(q6ec5g.777)..id(q6ec5g.779)"/></ims>
<move cont="false_cont" interj="false_interj" rep="none" aban="false_aban" meta="false_meta" id="q6ec5.g.move.139"  label="instruct"><nite:child href="q6ec5.g.timed-units.xml#id(q6ec5g.780)..id(q6ec5g.796)"/></move>
<ims id="q6ec5.g.move.140.5" ><nite:child href="q6ec5.g.timed-units.xml#id(q6ec5g.797)..id(q6ec5g.799)"/></ims>
<move interj="false_interj" rep="none" aban="false_aban" meta="false_meta" id="q6ec5.g.move.141"  label="instruct" cont="true_cont"><nite:child href="q6ec5.g.timed-units.xml#id(q6ec5g.800)..id(q6ec5g.813)"/></move>
<ims id="q6ec5.g.move.143.5" ><nite:child href="q6ec5.g.timed-units.xml#id(q6ec5g.814)"/></ims>
<move cont="false_cont" interj="false_interj" rep="none" aban="false_aban" meta="false_meta" id="q6ec5.g.move.144"  label="ready"><nite:child href="q6ec5.g.timed-units.xml#id(q6ec5g.815)..id(q6ec5g.816)"/></move>
<move cont="false_cont" interj="false_interj" rep="none" aban="false_aban" meta="false_meta" id="q6ec5.g.move.145"  label="clarify"><nite:child href="q6ec5.g.timed-units.xml#id(q6ec5g.818)..id(q6ec5g.827)"/></move>
<ims id="q6ec5.g.move.147.5" ><nite:child href="q6ec5.g.timed-units.xml#id(q6ec5g.828)"/></ims>
<move cont="false_cont" interj="false_interj" rep="none" aban="false_aban" meta="false_meta" id="q6ec5.g.move.148"  label="reply_w"><nite:child href="q6ec5.g.timed-units.xml#id(q6ec5g.829)..id(q6ec5g.833)"/></move>
<ims id="q6ec5.g.move.149.5" ><nite:child href="q6ec5.g.timed-units.xml#id(q6ec5g.834)..id(q6ec5g.836)"/></ims>
<move interj="false_interj" rep="none" aban="false_aban" meta="false_meta" id="q6ec5.g.move.150"  label="instruct" cont="true_cont"><nite:child href="q6ec5.g.timed-units.xml#id(q6ec5g.837)..id(q6ec5g.847)"/></move>
<ims id="q6ec5.g.move.151.5" ><nite:child href="q6ec5.g.timed-units.xml#id(q6ec5g.849)"/></ims>
<move interj="false_interj" rep="none" meta="false_meta" id="q6ec5.g.move.152"  label="instruct" aban="true_aban" cont="true_cont"><nite:child href="q6ec5.g.timed-units.xml#id(q6ec5g.850)..id(q6ec5g.851.1)"/></move>
<ims id="q6ec5.g.move.154.5" ><nite:child href="q6ec5.g.timed-units.xml#id(q6ec5g.852)"/></ims>
<move cont="false_cont" interj="false_interj" rep="none" aban="false_aban" meta="false_meta" id="q6ec5.g.move.155"  label="reply_y"><nite:child href="q6ec5.g.timed-units.xml#id(q6ec5g.853)"/></move>
<ims id="q6ec5.g.move.156.5" ><nite:child href="q6ec5.g.timed-units.xml#id(q6ec5g.854)..id(q6ec5g.859)"/></ims>
<move cont="false_cont" interj="false_interj" rep="none" meta="false_meta" id="q6ec5.g.move.157"  label="instruct" aban="true_aban"><nite:child href="q6ec5.g.timed-units.xml#id(q6ec5g.860)..id(q6ec5g.864)"/></move>
<ims id="q6ec5.g.move.157.5" ><nite:child href="q6ec5.g.timed-units.xml#id(q6ec5g.865)"/></ims>
<move cont="false_cont" interj="false_interj" rep="none" aban="false_aban" meta="false_meta" id="q6ec5.g.move.158"  label="query_yn"><nite:child href="q6ec5.g.timed-units.xml#id(q6ec5g.866)..id(q6ec5g.869)"/></move>
<ims id="q6ec5.g.move.160.5" ><nite:child href="q6ec5.g.timed-units.xml#id(q6ec5g.871)..id(q6ec5g.875)"/></ims>
<move interj="false_interj" rep="none" aban="false_aban" meta="false_meta" id="q6ec5.g.move.161"  label="instruct" cont="true_cont"><nite:child href="q6ec5.g.timed-units.xml#id(q6ec5g.876)..id(q6ec5g.883)"/></move>
<ims id="q6ec5.g.move.162.5" ><nite:child href="q6ec5.g.timed-units.xml#id(q6ec5g.884)..id(q6ec5g.885)"/></ims>
<move cont="false_cont" interj="false_interj" rep="none" aban="false_aban" meta="false_meta" id="q6ec5.g.move.163"  label="reply_w"><nite:child href="q6ec5.g.timed-units.xml#id(q6ec5g.886)..id(q6ec5g.889)"/></move>
<ims id="q6ec5.g.move.164.5" ><nite:child href="q6ec5.g.timed-units.xml#id(q6ec5g.890)..id(q6ec5g.893)"/></ims>
<move cont="false_cont" interj="false_interj" rep="none" aban="false_aban" meta="false_meta" id="q6ec5.g.move.165"  label="ready"><nite:child href="q6ec5.g.timed-units.xml#id(q6ec5g.894)..id(q6ec5g.897)"/></move>
<ims id="q6ec5.g.move.165.5" ><nite:child href="q6ec5.g.timed-units.xml#id(q6ec5g.899)..id(q6ec5g.900)"/></ims>
<move cont="false_cont" interj="false_interj" rep="none" aban="false_aban" meta="false_meta" id="q6ec5.g.move.166"  label="align"><nite:child href="q6ec5.g.timed-units.xml#id(q6ec5g.901)..id(q6ec5g.905)"/></move>
<ims id="q6ec5.g.move.168.5" ><nite:child href="q6ec5.g.timed-units.xml#id(q6ec5g.907)"/></ims>
<move cont="false_cont" interj="false_interj" rep="none" aban="false_aban" meta="false_meta" id="q6ec5.g.move.169"  label="reply_y"><nite:child href="q6ec5.g.timed-units.xml#id(q6ec5g.908)"/></move>
<ims id="q6ec5.g.move.170.5" ><nite:child href="q6ec5.g.timed-units.xml#id(q6ec5g.909)..id(q6ec5g.911)"/></ims>
<move cont="false_cont" interj="false_interj" rep="none" aban="false_aban" meta="false_meta" id="q6ec5.g.move.171"  label="instruct"><nite:child href="q6ec5.g.timed-units.xml#id(q6ec5g.912)..id(q6ec5g.931)"/></move>
<ims id="q6ec5.g.move.172.5" ><nite:child href="q6ec5.g.timed-units.xml#id(q6ec5g.933)..id(q6ec5g.935)"/></ims>
<move cont="false_cont" interj="false_interj" rep="none" aban="false_aban" meta="false_meta" id="q6ec5.g.move.173"  label="ready"><nite:child href="q6ec5.g.timed-units.xml#id(q6ec5g.936)"/></move>
<move cont="false_cont" interj="false_interj" rep="none" aban="false_aban" meta="false_meta" id="q6ec5.g.move.174"  label="align"><nite:child href="q6ec5.g.timed-units.xml#id(q6ec5g.938)..id(q6ec5g.953)"/></move>
<ims id="q6ec5.g.move.177.5" ><nite:child href="q6ec5.g.timed-units.xml#id(q6ec5g.954)"/></ims>
<move interj="false_interj" rep="none" aban="false_aban" meta="false_meta" id="q6ec5.g.move.178"  label="align" cont="true_cont"><nite:child href="q6ec5.g.timed-units.xml#id(q6ec5g.955)..id(q6ec5g.966)"/></move>
<ims id="q6ec5.g.move.179.5" ><nite:child href="q6ec5.g.timed-units.xml#id(q6ec5g.967)"/></ims>
<move interj="false_interj" rep="none" aban="false_aban" meta="false_meta" id="q6ec5.g.move.180"  label="align" cont="true_cont"><nite:child href="q6ec5.g.timed-units.xml#id(q6ec5g.968)..id(q6ec5g.974)"/></move>
<ims id="q6ec5.g.move.181.5" ><nite:child href="q6ec5.g.timed-units.xml#id(q6ec5g.975)..id(q6ec5g.977)"/></ims>
<move interj="false_interj" rep="none" aban="false_aban" meta="false_meta" id="q6ec5.g.move.182"  label="align" cont="true_cont"><nite:child href="q6ec5.g.timed-units.xml#id(q6ec5g.978)..id(q6ec5g.1000)"/></move>
<ims id="q6ec5.g.move.183.5" ><nite:child href="q6ec5.g.timed-units.xml#id(q6ec5g.1001)"/></ims>
<move cont="false_cont" interj="false_interj" rep="none" aban="false_aban" meta="false_meta" id="q6ec5.g.move.184"  label="query_w"><nite:child href="q6ec5.g.timed-units.xml#id(q6ec5g.1002)..id(q6ec5g.1005)"/></move>
<ims id="q6ec5.g.move.185.5" ><nite:child href="q6ec5.g.timed-units.xml#id(q6ec5g.1007)..id(q6ec5g.1009)"/></ims>
<move cont="false_cont" interj="false_interj" rep="none" aban="false_aban" meta="false_meta" id="q6ec5.g.move.186"  label="acknowledge"><nite:child href="q6ec5.g.timed-units.xml#id(q6ec5g.1010)"/></move>
<ims id="q6ec5.g.move.187.5" ><nite:child href="q6ec5.g.timed-units.xml#id(q6ec5g.1011)"/></ims>
<move cont="false_cont" interj="false_interj" rep="none" aban="false_aban" meta="false_meta" id="q6ec5.g.move.188"  label="ready"><nite:child href="q6ec5.g.timed-units.xml#id(q6ec5g.1012)"/></move>
<ims id="q6ec5.g.move.188.4" ><nite:child href="q6ec5.g.timed-units.xml#id(q6ec5g.1013)"/></ims>
<move cont="false_cont" interj="false_interj" rep="none" aban="false_aban" meta="false_meta" id="q6ec5.g.move.188.9"  label="align"><nite:child href="q6ec5.g.timed-units.xml#id(q6ec5g.1014)..id(q6ec5g.1016)"/></move>
<ims id="q6ec5.g.move.190.5" ><nite:child href="q6ec5.g.timed-units.xml#id(q6ec5g.1018)..id(q6ec5g.1020)"/></ims>
<move cont="false_cont" interj="false_interj" rep="none" aban="false_aban" meta="false_meta" id="q6ec5.g.move.191"  label="acknowledge"><nite:child href="q6ec5.g.timed-units.xml#id(q6ec5g.1021)..id(q6ec5g.1023.1)"/></move>
<ims id="q6ec5.g.move.192.5" ><nite:child href="q6ec5.g.timed-units.xml#id(q6ec5g.1025)"/></ims>
<move cont="false_cont" interj="false_interj" rep="none" aban="false_aban" meta="false_meta" id="q6ec5.g.move.193"  label="align"><nite:child href="q6ec5.g.timed-units.xml#id(q6ec5g.1026)..id(q6ec5g.1036)"/></move>
<ims id="q6ec5.g.move.194.5" ><nite:child href="q6ec5.g.timed-units.xml#id(q6ec5g.1038)"/></ims>
<move cont="false_cont" interj="false_interj" rep="none" aban="false_aban" meta="false_meta" id="q6ec5.g.move.195"  label="acknowledge"><nite:child href="q6ec5.g.timed-units.xml#id(q6ec5g.1039)..id(q6ec5g.1043)"/></move>
<move cont="false_cont" interj="false_interj" rep="none" aban="false_aban" meta="false_meta" id="q6ec5.g.move.196"  label="instruct"><nite:child href="q6ec5.g.timed-units.xml#id(q6ec5g.1045)..id(q6ec5g.1049)"/></move>
<ims id="q6ec5.g.move.196.6" ><nite:child href="q6ec5.g.timed-units.xml#id(q6ec5g.1050)..id(q6ec5g.1052)"/></ims>
</nite:root>

